mpy_utils/__init__.py
mpy_utils/replcontrol.py
mpy_utils/replfuseops.py
mpy_utils-0.1.13.data/scripts/mpy-download
mpy_utils-0.1.13.data/scripts/mpy-fuse
mpy_utils-0.1.13.data/scripts/mpy-reset
mpy_utils-0.1.13.data/scripts/mpy-sync
mpy_utils-0.1.13.data/scripts/mpy-upload
mpy_utils-0.1.13.data/scripts/mpy-watch
mpy_utils-0.1.13.dist-info/LICENSE
mpy_utils-0.1.13.dist-info/METADATA
mpy_utils-0.1.13.dist-info/WHEEL
mpy_utils-0.1.13.dist-info/top_level.txt
mpy_utils-0.1.13.dist-info/RECORD
