Metadata-Version: 2.1
Name: mpy-utils
Version: 0.1.13
Summary: MicroPython development utility programs
Home-page: http://github.com/nickzoic/mpy-utils/
Author: Nick Moore
Author-email: nick@zoic.org
License: MIT
Classifier: Development Status :: 3 - Alpha
Classifier: Environment :: Console
Classifier: Intended Audience :: Developers
Classifier: License :: OSI Approved :: MIT License
Classifier: Programming Language :: Python :: 3 :: Only
Classifier: Topic :: Software Development :: Embedded Systems
License-File: LICENSE
Requires-Dist: fusepy (>=3)
Requires-Dist: pyserial (>=3)
